octoblox/__init__.py
octoblox-0.5.0.dist-info/LICENSE
octoblox-0.5.0.dist-info/METADATA
octoblox-0.5.0.dist-info/WHEEL
octoblox-0.5.0.dist-info/top_level.txt
octoblox-0.5.0.dist-info/zip-safe
octoblox-0.5.0.dist-info/RECORD
