Metadata-Version: 2.1
Name: octoblox
Version: 0.5.0
Summary: Infoblox provider for octoDNS
Home-page: https://github.com/asyncon/octoblox
Author: asyncon
Author-email: 53700266+asyncon@users.noreply.github.com
License: MIT
Project-URL: Bug Tracker, https://github.com/asyncon/octoblox/issues
Project-URL: Documentation, https://github.com/asyncon/octoblox
Project-URL: Source Code, https://github.com/asyncon/octoblox
Classifier: Development Status :: 3 - Alpha
Classifier: Intended Audience :: System Administrators
Classifier: Topic :: Internet :: Name Service (DNS)
Classifier: License :: OSI Approved :: MIT License
Classifier: Operating System :: OS Independent
Classifier: Programming Language :: Python
Classifier: Programming Language :: Python :: 3
Classifier: Programming Language :: Python :: 3.6
Classifier: Programming Language :: Python :: 3.7
Classifier: Programming Language :: Python :: 3.8
Classifier: Programming Language :: Python :: 3.9
Classifier: Programming Language :: Python :: 3.10
License-File: LICENSE
Requires-Dist: octodns
Requires-Dist: requests
Provides-Extra: dev
Requires-Dist: black ; extra == 'dev'
Requires-Dist: flake8 ; extra == 'dev'
Requires-Dist: flake8-bugbear ; extra == 'dev'
Requires-Dist: pytest ; extra == 'dev'
Requires-Dist: pytest-cov ; extra == 'dev'
Requires-Dist: requests-mock ; extra == 'dev'
